darkimg/__init__.py
darkimg/main.py
darkimg-0.0.1.dist-info/METADATA
darkimg-0.0.1.dist-info/WHEEL
darkimg-0.0.1.dist-info/top_level.txt
darkimg-0.0.1.dist-info/zip-safe
darkimg-0.0.1.dist-info/RECORD
