Metadata-Version: 2.1
Name: darkimg
Version: 0.0.1
Summary: Advanced image processer/drawer
Home-page: https://google.com
Author: darkdarcool30
Author-email: darkdarcool@gmail.com
License: MIT
Platform: UNKNOWN
Classifier: Programming Language :: Python :: 3
Classifier: License :: OSI Approved :: MIT License
Classifier: Operating System :: OS Independent
Requires-Python: >=3.6
